wh1tem0cha/__init__.py
wh1tem0cha/wh1tem0cha.py
wh1tem0cha-0.1.dist-info/LICENSE
wh1tem0cha-0.1.dist-info/METADATA
wh1tem0cha-0.1.dist-info/WHEEL
wh1tem0cha-0.1.dist-info/top_level.txt
wh1tem0cha-0.1.dist-info/RECORD
