Metadata-Version: 2.1
Name: wh1tem0cha
Version: 0.1
Summary: Python Module for Parsing & Reverse Engineering Mach-O Executables.
Home-page: https://github.com/CYB3RMX/Wh1teM0cha
Author: CYB3RMX
Author-email: cyb3rmx0@gmail.com
Project-URL: Bug Tracker, https://github.com/CYB3RMX/Wh1teM0cha/issues
Classifier: Programming Language :: Python :: 3
Classifier: License :: OSI Approved :: GNU General Public License (GPL)
Classifier: Operating System :: OS Independent
Requires-Python: >=3.9
License-File: LICENSE
